mys7erio_dummy/__init__.py
mys7erio_dummy/__main__.py
mys7erio_dummy/main.py
mys7erio_dummy-0.1.0.dist-info/METADATA
mys7erio_dummy-0.1.0.dist-info/WHEEL
mys7erio_dummy-0.1.0.dist-info/entry_points.txt
mys7erio_dummy-0.1.0.dist-info/RECORD
